AUTHORS.rst
CONTRIBUTING.rst
HISTORY.rst
LICENSE
MANIFEST.in
README.rst
setup.cfg
setup.py
apps/pilot/jadolfbr/copy_top_each_strategy.py
apps/pilot/jadolfbr/glycan_basic_LCM_protocol.py
apps/pilot/jadolfbr/nnk_scorefxn.py
apps/public/antibody_benchmark_utils/RunRosettaBenchmarksMPI.py
apps/public/antibody_benchmark_utils/bm-RAbD_Jade.py
apps/public/antibody_benchmark_utils/bm-calculate_graft_closure_rabd.py
apps/public/antibody_benchmark_utils/bm-calculate_plot_mc_acceptance_rabd.py
apps/public/antibody_benchmark_utils/bm-calculate_recoveries_and_risk_ratios.py
apps/public/antibody_benchmark_utils/bm-output_all_clusters.py
apps/public/antibody_benchmark_utils/bm-plot_features.py
apps/public/antibody_benchmark_utils/bm-run_rabd_benchmarks.py
apps/public/antibody_utils/RAbD_Jade.py
apps/public/antibody_utils/convert_IMGT_to_fasta.py
apps/public/antibody_utils/create_features_json.py
apps/public/antibody_utils/generate_rabd_features_dbs.py
apps/public/antibody_utils/match_antibody_structures.py
apps/public/antibody_utils/order_ab_chains.py
apps/public/antibody_utils/split_antibody_components.py
apps/public/general/canceljobs.py
apps/public/general/convert_fig.py
apps/public/general/genscript_to_fasta.py
apps/public/general/get_seq.py
apps/public/general/rename_designs.py
apps/public/pdb_utils/place_TERs.py
apps/public/pdb_utils/strip_ANISOU.py
apps/public/pdb_utils/strip_ter.py
apps/public/pyrosetta/build_loop_pyrosetta.py
apps/public/pyrosetta/find_my_glycans.py
apps/public/pyrosetta/find_my_residues.py
apps/public/pyrosetta/get_mutation_energy.py
apps/public/rosetta/RunRosettaDBMode.py
apps/public/rosetta/RunRosettaMPI.py
apps/public/rosetta/check_missing_rosetta_nstruct.py
apps/public/rosetta/create_score_json_from_scored_decoys.py
apps/public/rosetta/insert_natives_table_into_features_db.py
apps/public/rosetta/score_analysis.py
bio_jade.egg-info/PKG-INFO
bio_jade.egg-info/SOURCES.txt
bio_jade.egg-info/dependency_links.txt
bio_jade.egg-info/not-zip-safe
bio_jade.egg-info/requires.txt
bio_jade.egg-info/top_level.txt
docs/Makefile
docs/authors.rst
docs/conf.py
docs/contributing.rst
docs/history.rst
docs/index.rst
docs/installation.rst
docs/jade.rst
