Metadata-Version: 1.1
Name: bio-jade
Version: 1.0
Summary: A repository for modules and applications to aid in the design and analysis of Biological molecules, especially when working with Rosetta or PyRosetta.
Home-page: https://github.com/SchiefLab/Jade
Author: Jared Adolf-Bryfogle
Author-email: jadolfbr@gmail.com
License: BSD
Keywords: rosetta pyrosetta biology protein design bioinformatics carbohydrates pymol biochemistry modeling pdb
Platform: UNKNOWN
Classifier: License :: OSI Approved :: BSD License
Classifier: Natural Language :: English
Classifier: Topic :: Scientific/Engineering
Classifier: Topic :: Scientific/Engineering :: Bio-Informatics
Classifier: Topic :: Scientific/Engineering :: Chemistry
Classifier: Topic :: Scientific/Engineering :: Medical Science Apps.
Classifier: Topic :: Utilities
